README.rst
_ksi.c
ksi.py
setup.cfg
setup.py
ksi_python.egg-info/PKG-INFO
ksi_python.egg-info/SOURCES.txt
ksi_python.egg-info/dependency_links.txt
ksi_python.egg-info/top_level.txt