Metadata-Version: 1.0
Name: ksi-python
Version: 1.0.0
Summary: Python wrapper for libksi, a library for accessing Guardtime KSI service
Home-page: https://github.com/guardtime/ksi-python
Author: Guardtime
Author-email: info@guardtime.com
License: Apache 2.0
Platform: any
